riscv/__init__.py
riscv/__main__.py
riscv/_riscv.cpython-311-x86_64-linux-gnu.so
riscv/_utils.py
riscv/_version.py
riscv/dev.py
riscv/isa.py
riscv/py.typed
riscv/data/bin/spike
riscv/data/include/fdt/fdt.h
riscv/data/include/fdt/libfdt.h
riscv/data/include/fdt/libfdt_env.h
riscv/data/include/fesvr/byteorder.h
riscv/data/include/fesvr/config.h
riscv/data/include/fesvr/context.h
riscv/data/include/fesvr/device.h
riscv/data/include/fesvr/dtm.h
riscv/data/include/fesvr/elf.h
riscv/data/include/fesvr/elfloader.h
riscv/data/include/fesvr/htif.h
riscv/data/include/fesvr/htif_hexwriter.h
riscv/data/include/fesvr/htif_pthread.h
riscv/data/include/fesvr/memif.h
riscv/data/include/fesvr/option_parser.h
riscv/data/include/fesvr/rfb.h
riscv/data/include/fesvr/syscall.h
riscv/data/include/fesvr/term.h
riscv/data/include/fesvr/tsi.h
riscv/data/include/riscv/abstract_device.h
riscv/data/include/riscv/abstract_interrupt_controller.h
riscv/data/include/riscv/cachesim.h
riscv/data/include/riscv/cfg.h
riscv/data/include/riscv/common.h
riscv/data/include/riscv/csrs.h
riscv/data/include/riscv/debug_defines.h
riscv/data/include/riscv/debug_module.h
riscv/data/include/riscv/debug_rom_defines.h
riscv/data/include/riscv/decode.h
riscv/data/include/riscv/devices.h
riscv/data/include/riscv/disasm.h
riscv/data/include/riscv/dts.h
riscv/data/include/riscv/encoding.h
riscv/data/include/riscv/entropy_source.h
riscv/data/include/riscv/extension.h
riscv/data/include/riscv/isa_parser.h
riscv/data/include/riscv/jtag_dtm.h
riscv/data/include/riscv/log_file.h
riscv/data/include/riscv/memtracer.h
riscv/data/include/riscv/mmu.h
riscv/data/include/riscv/platform.h
riscv/data/include/riscv/processor.h
riscv/data/include/riscv/remote_bitbang.h
riscv/data/include/riscv/rocc.h
riscv/data/include/riscv/sim.h
riscv/data/include/riscv/simif.h
riscv/data/include/riscv/trap.h
riscv/data/include/riscv/triggers.h
riscv/data/include/riscv/vector_unit.h
spike-0.0.5.dev17.dist-info/METADATA
spike-0.0.5.dev17.dist-info/WHEEL
spike-0.0.5.dev17.dist-info/top_level.txt
spike-0.0.5.dev17.dist-info/RECORD
spike-0.0.5.dev17.dist-info/licenses/LICENSE
