Metadata-Version: 2.1
Name: spike
Version: 0.0.5.dev17
Summary: Python Bindings of Spike RISC-V ISA Simulator
Author-email: LIU Yu <liuyu@huimtlab.org>
License: Apache License
Project-URL: Homepage, https://github.com/liuyu81/pyspike
Keywords: RISC-V,spike,ISA,simulator,verification
Classifier: Development Status :: 4 - Beta
Classifier: Intended Audience :: Developers
Classifier: Intended Audience :: Science/Research
Classifier: Framework :: cocotb
Classifier: Framework :: Pytest
Classifier: Framework :: Sphinx
Classifier: Framework :: tox
Classifier: Operating System :: POSIX :: Linux
Classifier: Programming Language :: C++
Classifier: Programming Language :: Python
Classifier: Programming Language :: Python :: 3
Classifier: Programming Language :: Python :: 3.8
Classifier: Programming Language :: Python :: 3.9
Classifier: Programming Language :: Python :: 3.10
Classifier: Programming Language :: Python :: 3.11
Classifier: Programming Language :: Python :: 3.12
Classifier: Topic :: Scientific/Engineering :: Electronic Design Automation (EDA)
Classifier: Topic :: Software Development :: Disassemblers
Classifier: Topic :: Software Development :: Libraries
Classifier: Topic :: Software Development :: Libraries :: Python Modules
Classifier: Topic :: Software Development :: Embedded Systems
Classifier: Topic :: Software Development :: Quality Assurance
Classifier: Topic :: Software Development :: Testing
Classifier: Typing :: Typed
Requires-Python: >=3.8
License-File: LICENSE
Provides-Extra: dev
Requires-Dist: auditwheel; extra == "dev"
Requires-Dist: build; extra == "dev"
Requires-Dist: packaging>=25; extra == "dev"
Requires-Dist: patchelf; extra == "dev"
Requires-Dist: pexpect; extra == "dev"
Requires-Dist: pip>=23; extra == "dev"
Requires-Dist: pybind11[global]>3; extra == "dev"
Requires-Dist: pytest; extra == "dev"
Requires-Dist: pytest-asyncio; extra == "dev"
Requires-Dist: pytest-cov; extra == "dev"
Requires-Dist: pytest-mypy; extra == "dev"
Requires-Dist: pytest-pylint; extra == "dev"
Requires-Dist: pytest-repeat; extra == "dev"
Requires-Dist: pytest-timeout; extra == "dev"
Requires-Dist: setuptools>=75; extra == "dev"
Requires-Dist: setuptools-scm[toml]>=9; extra == "dev"
Requires-Dist: twine; extra == "dev"
Requires-Dist: wheel; extra == "dev"
